rdecscustomer/__init__.py
rdecscustomer/ec_DatabaseOperations.py
rdecscustomer/ec_Metadata.py
rdecscustomer/ec_Utility.py
rdecscustomer/ec_customerECSInterface.py
rdecscustomer/ec_customer_demo.py
rdecscustomer/mainModel.py
rdecscustomer-1.2.7.dist-info/METADATA
rdecscustomer-1.2.7.dist-info/WHEEL
rdecscustomer-1.2.7.dist-info/top_level.txt
rdecscustomer-1.2.7.dist-info/RECORD
